schemable/__init__.py
schemable/__version__.py
schemable/base.py
schemable/schema.py
schemable/transforms.py
schemable/validators.py
schemable-0.5.0.dist-info/METADATA
schemable-0.5.0.dist-info/RECORD
schemable-0.5.0.dist-info/WHEEL
schemable-0.5.0.dist-info/top_level.txt
